bmp384/__init__.py
bmp384/bmp384.py
bmp384-0.1.0.dist-info/LICENSE
bmp384-0.1.0.dist-info/METADATA
bmp384-0.1.0.dist-info/WHEEL
bmp384-0.1.0.dist-info/top_level.txt
bmp384-0.1.0.dist-info/RECORD
