Metadata-Version: 2.1
Name: bmp384
Version: 0.1.0
Summary: Raspberry Pi Pico Micropython library to interact with the Bosch BMP384 Barometric pressure sensor
Home-page: https://github.com/cbraissant/bmp384-pico-driver
Author: Chris Braissant
Author-email: Chris Braissant <chrisbraissant@gmail.com>
License: Copyright (c) 2023 Chris Braissant
Project-URL: Repository, https://github.com/cbraissant/bmp384-pico-driver
Classifier: Development Status :: 3 - Alpha
Classifier: Operating System :: OS Independent
Classifier: License :: OSI Approved :: MIT License
Classifier: Intended Audience :: Developers
Classifier: Programming Language :: Python :: 3
Classifier: Programming Language :: Python :: 3.11
Classifier: Topic :: Software Development :: Embedded Systems
Requires-Python: >=3.8
License-File: LICENSE
